telegram_gateway/__init__.py
telegram_gateway/constants.py
telegram_gateway/enums.py
telegram_gateway/gateway.py
telegram_gateway/types.py
telegram_gateway-0.0.5.dist-info/METADATA
telegram_gateway-0.0.5.dist-info/WHEEL
telegram_gateway-0.0.5.dist-info/top_level.txt
telegram_gateway-0.0.5.dist-info/RECORD
