Metadata-Version: 2.2
Name: telegram-gateway
Version: 0.0.5
Summary: Interact with the Telegram Gateway API.
Author-email: GEOEGII555 <geoegii2001555@gmail.com>
Project-URL: Repository, https://github.com/GEOEGII555/telegram-gateway.git
Classifier: Programming Language :: Python :: 3
Classifier: Operating System :: OS Independent
Classifier: Typing :: Typed
Requires-Dist: requests
